azvalidator/__init__.py
azvalidator/apps.py
azvalidator/middleware.py
azvalidator/migrations/__init__.py
azvalidator/utils/__init__.py
django_azuread_token_validator-0.1.10.dist-info/licenses/LICENSE
django_azuread_token_validator-0.1.10.dist-info/METADATA
django_azuread_token_validator-0.1.10.dist-info/WHEEL
django_azuread_token_validator-0.1.10.dist-info/top_level.txt
django_azuread_token_validator-0.1.10.dist-info/RECORD
